swifty/__init__.py
swifty/rates.py
swifty-0.1.0.dist-info/licenses/LICENSE
swifty-0.1.0.dist-info/METADATA
swifty-0.1.0.dist-info/WHEEL
swifty-0.1.0.dist-info/top_level.txt
swifty-0.1.0.dist-info/RECORD
