Metadata-Version: 2.4
Name: swifty
Version: 0.1.0
Summary: SDK for building multichain wallets and real-time financial dashboards.
Author: Swifty Labs
License: MIT
Project-URL: Homepage, https://github.com/swifty-lab
Classifier: Programming Language :: Python :: 3
Classifier: License :: OSI Approved :: MIT License
Classifier: Development Status :: 2 - Pre-Alpha
License-File: LICENSE
Requires-Dist: aiohttp>=3.8.0
Dynamic: license-file
